UsamaAliceWhite/__init__.py
UsamaAliceWhite/Logging/Core.py
UsamaAliceWhite/Logging/__init__.py
usamaalicewhite-0.0.0.dist-info/METADATA
usamaalicewhite-0.0.0.dist-info/WHEEL
usamaalicewhite-0.0.0.dist-info/top_level.txt
usamaalicewhite-0.0.0.dist-info/RECORD
