Metadata-Version: 2.4
Name: UsamaAliceWhite
Version: 0.0.0
Summary: A simple, one-line utility for instant professional logging.
Author: UsamaAliceWhite
Classifier: Programming Language :: Python :: 3
Classifier: License :: OSI Approved :: MIT License
Classifier: Operating System :: OS Independent
Requires-Python: >=3.10
